[{"criteria detail":"Elegant mansion set in the heart of London’s Mayfair\rMax. capacity 48 cabaret, proposal based on exclusive hire ","criteria match":".94","currency":"£ Sterling","latitude":51.5078375,"longitude":-0.1468016,"name":"Dartmouth House","status":"Held : Option expires 26/06/2026","total cost":"14803.2","town":"London","website":"www.dartmouthhouse.co.uk/"},{"criteria detail":"Tucked away in leafy south-west London, this 15-century country estate was home to the Bishops of London until 1975.","criteria match":"1","currency":"£ Sterling","latitude":51.4707092,"longitude":-0.2159675,"name":"Fulham Palace","status":"Held","total cost":"21300","town":"London","website":"www.fulhampalace.org"},{"criteria detail":"On the edge of Hampstead Heath surrounded by landscaped gardens","criteria match":"1","currency":"£ Sterling","latitude":51.5713882,"longitude":-0.1674543,"name":"Kenwood House","status":"Held","total cost":"15954","town":"London","website":"www.english-heritage.org.uk/visit/places/kenwood/"},{"criteria detail":"Purpose-built venue offering several spaces, perfect for all types of events from conferences to meetings to drinks receptions to workshops","criteria match":".9","currency":"£ Sterling","latitude":51.5018272,"longitude":-0.0005759,"name":"The Line","status":"Second Option : Update due 25/06/2026","total cost":"18782.4","town":"London","website":"https://thelinevenue.london/"},{"criteria detail":"Set on a pontoon between Cleopatra’s Needle and Waterloo Bridge, Woods Quay is a new dining and entertainment venue\rProposal based on exclusive hire  ","criteria match":".92","currency":"£ Sterling","latitude":51.5093698,"longitude":-0.1186222,"name":"Woods Quay","status":"Held","total cost":"48240","town":"London","website":"www.woodsquay.co.uk"}]